Metadata-Version: 2.1
Name: odoo12-addon-account-invoice-supplierinfo-update-qty-multiplier
Version: 12.0.1.0.1
Summary: In the invoice Supplierinfo wizard, allow to change the Quantity Multiplier field
Home-page: https://github.com/OCA/account-invoicing
Author: GRAP,Odoo Community Association (OCA)
Author-email: support@odoo-community.org
License: AGPL-3
Platform: UNKNOWN
Classifier: Programming Language :: Python
Classifier: Framework :: Odoo
Classifier: Framework :: Odoo :: 12.0
Classifier: License :: OSI Approved :: GNU Affero General Public License v3
Requires-Python: >=3.5
Requires-Dist: odoo12-addon-account-invoice-supplierinfo-update
Requires-Dist: odoo12-addon-product-supplierinfo-qty-multiplier
Requires-Dist: odoo <12.1dev,>=12.0a
